hand_detection_v5/__init__.py
hand_detection_v5/hand_detection.py
hand_detection_v5-0.4.1.dist-info/LICENSE
hand_detection_v5-0.4.1.dist-info/METADATA
hand_detection_v5-0.4.1.dist-info/WHEEL
hand_detection_v5-0.4.1.dist-info/top_level.txt
hand_detection_v5-0.4.1.dist-info/RECORD
